{"playGetWidgetV2":{"data":[{"__typename":"PlayWidgetChannel","ID":"10818","title":"Test - Mirror","widgetType":"WATCH_AGAIN","appLink":"tokopedia://webview?url=https%3A%2F%2Fwww.tokopedia.com%2Fplay%2Fupdate","webLink":"https://www.tokopedia.com/play/update","startTime":"3 October 2020 - 15:00","config":{"hasPromo":false,"isReminderSet":false},"partner":{"ID":"2248809","name":"Haha Accessories"},"video":{"ID":"7362","type":"live","coverUrl":"https://ecs7.tokopedia.net/img/cache/700/attachment/2020/8/11/inv/inv_0c7ecb34-6642-4b5b-9da4-c17a4fe14279.jpg","streamSource":"https://commondatastorage.googleapis.com/gtv-videos-bucket/sample/BigBuckBunny.mp4","isShowTotalView":true,"isLive":false},"stats":{"view":{"formatted":"528"}}},{"__typename":"PlayWidgetChannel","ID":"11828","title":"Test - Youtube live landscape","widgetType":"WATCH_AGAIN","appLink":"tokopedia://webview?url=https%3A%2F%2Fwww.tokopedia.com%2Fplay%2Fupdate","webLink":"https://www.tokopedia.com/play/update","startTime":"17 September 2020 - 12:18","config":{"hasPromo":false,"isReminderSet":false},"partner":{"ID":"2248809","name":"Haha Accessories"},"video":{"ID":"7767","type":"live","coverUrl":"https://ecs7.tokopedia.net/img/jJtrdn/2020/9/17/c10f607d-55de-435f-8093-e2d846bbc1b1.jpg","streamSource":"https://commondatastorage.googleapis.com/gtv-videos-bucket/sample/BigBuckBunny.mp4","isShowTotalView":true,"isLive":false},"stats":{"view":{"formatted":"72"}}},{"__typename":"PlayWidgetChannel","ID":"11657","title":"Test - Katalon Automation VOD","widgetType":"LIVE","appLink":"tokopedia://webview?url=https%3A%2F%2Fwww.tokopedia.com%2Fplay%2Fupdate","webLink":"https://www.tokopedia.com/play/update","startTime":"14 September 2020 - 14:04","config":{"hasPromo":false,"isReminderSet":false},"partner":{"ID":"2248809","name":"Haha Accessories"},"video":{"ID":"7510","type":"youtube","coverUrl":"https://ecs7.tokopedia.net/img/jJtrdn/2020/9/14/95c8e78e-33e8-4f1a-91a1-bf2a5596c1a5.jpg","streamSource":"https://commondatastorage.googleapis.com/gtv-videos-bucket/sample/BigBuckBunny.mp4","isShowTotalView":true,"isLive":false},"stats":{"view":{"formatted":"31"}}},{"__typename":"PlayWidgetChannel","ID":"11202","title":"Test - Android Haha Accessories 1234567890","widgetType":"COMING_SOON","appLink":"tokopedia://webview?url=https%3A%2F%2Fwww.tokopedia.com%2Fplay%2Fupdate","webLink":"https://www.tokopedia.com/play/update","startTime":"31 October 2020 - 10:14","config":{"hasPromo":false,"isReminderSet":false},"partner":{"ID":"2248809","name":"Haha Accessories"},"video":{"ID":"7181","type":"live","coverUrl":"https://ecs7.tokopedia.net/img/cache/700/attachment/2020/9/2/inv/inv_b4cb80bc-aa3c-44b9-b368-ca373c488db1.jpg","streamSource":"https://commondatastorage.googleapis.com/gtv-videos-bucket/sample/BigBuckBunny.mp4","isShowTotalView":true,"isLive":false},"stats":{"view":{"formatted":"14"}}}],"meta":{"isAutoRefresh":true,"autoRefreshTimer":30,"widgetTitle":"Yuk, tonton sekarang","buttonText":"Lihat semua","widgetBackground":"","autoplayAmount":2,"autoplay":false,"buttonApplink":"tokopedia://webview?titlebar=false&url=https%3A%2F%2Fwww.tokopedia.com%2Fplay%2Fchannels%2F","buttonWeblink":"www.tokopedia.com/play/channels","overlayImage":"https://ecs7.tokopedia.net/stessayalp/KV-Left-Widget-September.png","overlayImageAppLink":"tokopedia://webview?titlebar=false&url=https%3A%2F%2Fwww.tokopedia.com%2Fplay%2Fchannels%2F","overlayImageWebLink":"www.tokopedia.com/play/channels","gradient":["#57E9FF","#009ad6"],"serverTimeOffset":"1601964387","maxAutoplayCell":30}}}